[{"Name":"C Header","Bytes":59241,"CodeBytes":0,"Lines":1727,"Code":1047,"Comment":392,"Blank":288,"Complexity":0,"Count":35,"WeightedComplexity":0,"Files":[{"Language":"C Header","PossibleLanguages":["C Header"],"Filename":"activity_estimation.h","Extension":"h","Location":"activity_estimation.h","Symlocation":"","Bytes":140,"Lines":2,"Code":1,"Comment":0,"Blank":1,"Complexity":0,"WeightedComplexity":0,"Hash":null,"Callback":null,"Binary":false,"Minified":false,"Generated":false},{"Language":"C Header","PossibleLanguages":["C Header"],"Filename":"ast_optimizations.h","Extension":"h","Location":"ast_optimizations.h","Symlocation":"","Bytes":100,"Lines":4,"Code":2,"Comment":0,"Blank":2,"Complexity":0,"WeightedComplexity":0,"Hash":null,"Callback":null,"Binary":false,"Minified":false,"Generated":false},{"Language":"C Header","PossibleLanguages":["C Header"],"Filename":"globals.h","Extension":"h","Location":"globals.h","Symlocation":"","Bytes":1329,"Lines":56,"Code":38,"Comment":3,"Blank":15,"Complexity":0,"WeightedComplexity":0,"Hash":null,"Callback":null,"Binary":false,"Minified":false,"Generated":false},{"Language":"C Header","PossibleLanguages":["C Header"],"Filename":"ast_util.h","Extension":"h","Location":"ast_util.h","Symlocation":"","Bytes":1296,"Lines":24,"Code":18,"Comment":0,"Blank":6,"Complexity":0,"WeightedComplexity":0,"Hash":null,"Callback":null,"Binary":false,"Minified":false,"Generated":false},{"Language":"C Header","PossibleLanguages":["C Header"],"Filename":"queue.h","Extension":"h","Location":"queue.h","Symlocation":"","Bytes":1804,"Lines":55,"Code":22,"Comment":28,"Blank":5,"Complexity":0,"WeightedComplexity":0,"Hash":null,"Callback":null,"Binary":false,"Minified":false,"Generated":false},{"Language":"C Header","PossibleLanguages":["C Header"],"Filename":"read_blif.h","Extension":"h","Location":"read_blif.h","Symlocation":"","Bytes":92,"Lines":8,"Code":4,"Comment":0,"Blank":4,"Complexity":0,"WeightedComplexity":0,"Hash":null,"Callback":null,"Binary":false,"Minified":false,"Generated":false},{"Language":"C Header","PossibleLanguages":["C Header"],"Filename":"errors.h","Extension":"h","Location":"errors.h","Symlocation":"","Bytes":176,"Lines":3,"Code":2,"Comment":0,"Blank":1,"Complexity":0,"WeightedComplexity":0,"Hash":null,"Callback":null,"Binary":false,"Minified":false,"Generated":false},{"Language":"C Header","PossibleLanguages":["C Header"],"Filename":"read_netlist.h","Extension":"h","Location":"read_netlist.h","Symlocation":"","Bytes":187,"Lines":7,"Code":6,"Comment":0,"Blank":1,"Complexity":0,"WeightedComplexity":0,"Hash":null,"Callback":null,"Binary":false,"Minified":false,"Generated":false},{"Language":"C Header","PossibleLanguages":["C Header"],"Filename":"sim_block.h","Extension":"h","Location":"sim_block.h","Symlocation":"","Bytes":538,"Lines":11,"Code":2,"Comment":8,"Blank":1,"Complexity":0,"WeightedComplexity":0,"Hash":null,"Callback":null,"Binary":false,"Minified":false,"Generated":false},{"Language":"C Header","PossibleLanguages":["C Header"],"Filename":"read_xml_config_file.h","Extension":"h","Location":"read_xml_config_file.h","Symlocation":"","Bytes":1291,"Lines":34,"Code":6,"Comment":24,"Blank":4,"Complexity":0,"WeightedComplexity":0,"Hash":null,"Callback":null,"Binary":false,"Minified":false,"Generated":false},{"Language":"C Header","PossibleLanguages":["C Header"],"Filename":"implicit_memory.h","Extension":"h","Location":"implicit_memory.h","Symlocation":"","Bytes":2399,"Lines":60,"Code":22,"Comment":28,"Blank":10,"Complexity":0,"WeightedComplexity":0,"Hash":null,"Callback":null,"Binary":false,"Minified":false,"Generated":false},{"Language":"C Header","PossibleLanguages":["C Header"],"Filename":"simulate_blif.h","Extension":"h","Location":"simulate_blif.h","Symlocation":"","Bytes":7392,"Lines":211,"Code":139,"Comment":27,"Blank":45,"Complexity":0,"WeightedComplexity":0,"Hash":null,"Callback":null,"Binary":false,"Minified":false,"Generated":false},{"Language":"C Header","PossibleLanguages":["C Header"],"Filename":"string_cache.h","Extension":"h","Location":"string_cache.h","Symlocation":"","Bytes":1706,"Lines":47,"Code":20,"Comment":22,"Blank":5,"Complexity":0,"WeightedComplexity":0,"Hash":null,"Callback":null,"Binary":false,"Minified":false,"Generated":false},{"Language":"C Header","PossibleLanguages":["C Header"],"Filename":"hashtable.h","Extension":"h","Location":"hashtable.h","Symlocation":"","Bytes":2450,"Lines":63,"Code":28,"Comment":30,"Blank":5,"Complexity":0,"WeightedComplexity":0,"Hash":null,"Callback":null,"Binary":false,"Minified":false,"Generated":false},{"Language":"C Header","PossibleLanguages":["C Header"],"Filename":"high_level_data.h","Extension":"h","Location":"high_level_data.h","Symlocation":"","Bytes":24,"Lines":2,"Code":1,"Comment":0,"Blank":1,"Complexity":0,"WeightedComplexity":0,"Hash":null,"Callback":null,"Binary":false,"Minified":false,"Generated":false},{"Language":"C Header","PossibleLanguages":["C Header"],"Filename":"types.h","Extension":"h","Location":"types.h","Symlocation":"","Bytes":15105,"Lines":543,"Code":395,"Comment":80,"Blank":68,"Complexity":0,"WeightedComplexity":0,"Hash":null,"Callback":null,"Binary":false,"Minified":false,"Generated":false},{"Language":"C Header","PossibleLanguages":["C Header"],"Filename":"memories.h","Extension":"h","Location":"memories.h","Symlocation":"","Bytes":3426,"Lines":112,"Code":69,"Comment":22,"Blank":21,"Complexity":0,"WeightedComplexity":0,"Hash":null,"Callback":null,"Binary":false,"Minified":false,"Generated":false},{"Language":"C Header","PossibleLanguages":["C Header"],"Filename":"netlist_check.h","Extension":"h","Location":"netlist_check.h","Symlocation":"","Bytes":142,"Lines":3,"Code":2,"Comment":0,"Blank":1,"Complexity":0,"WeightedComplexity":0,"Hash":null,"Callback":null,"Binary":false,"Minified":false,"Generated":false},{"Language":"C Header","PossibleLanguages":["C Header"],"Filename":"partial_map.h","Extension":"h","Location":"partial_map.h","Symlocation":"","Bytes":1401,"Lines":35,"Code":6,"Comment":25,"Blank":4,"Complexity":0,"WeightedComplexity":0,"Hash":null,"Callback":null,"Binary":false,"Minified":false,"Generated":false},{"Language":"C Header","PossibleLanguages":["C Header"],"Filename":"netlist_stats.h","Extension":"h","Location":"netlist_stats.h","Symlocation":"","Bytes":1787,"Lines":41,"Code":13,"Comment":22,"Blank":6,"Complexity":0,"WeightedComplexity":0,"Hash":null,"Callback":null,"Binary":false,"Minified":false,"Generated":false},{"Language":"C Header","PossibleLanguages":["C Header"],"Filename":"outputs.h","Extension":"h","Location":"outputs.h","Symlocation":"","Bytes":53,"Lines":2,"Code":1,"Comment":1,"Blank":0,"Complexity":0,"WeightedComplexity":0,"Hash":null,"Callback":null,"Binary":false,"Minified":false,"Generated":false},{"Language":"C Header","PossibleLanguages":["C Header"],"Filename":"netlist_optimizations.h","Extension":"h","Location":"netlist_optimizations.h","Symlocation":"","Bytes":68,"Lines":2,"Code":1,"Comment":1,"Blank":0,"Complexity":0,"WeightedComplexity":0,"Hash":null,"Callback":null,"Binary":false,"Minified":false,"Generated":false},{"Language":"C Header","PossibleLanguages":["C Header"],"Filename":"odin_util.h","Extension":"h","Location":"odin_util.h","Symlocation":"","Bytes":1631,"Lines":43,"Code":32,"Comment":0,"Blank":11,"Complexity":0,"WeightedComplexity":0,"Hash":null,"Callback":null,"Binary":false,"Minified":false,"Generated":false},{"Language":"C Header","PossibleLanguages":["C Header"],"Filename":"print_netlist.h","Extension":"h","Location":"print_netlist.h","Symlocation":"","Bytes":68,"Lines":2,"Code":1,"Comment":0,"Blank":1,"Complexity":0,"WeightedComplexity":0,"Hash":null,"Callback":null,"Binary":false,"Minified":false,"Generated":false},{"Language":"C Header","PossibleLanguages":["C Header"],"Filename":"netlist_create_from_ast.h","Extension":"h","Location":"netlist_create_from_ast.h","Symlocation":"","Bytes":205,"Lines":7,"Code":5,"Comment":0,"Blank":2,"Complexity":0,"WeightedComplexity":0,"Hash":null,"Callback":null,"Binary":false,"Minified":false,"Generated":false},{"Language":"C Header","PossibleLanguages":["C Header"],"Filename":"verilog_bison_user_defined.h","Extension":"h","Location":"verilog_bison_user_defined.h","Symlocation":"","Bytes":21,"Lines":1,"Code":1,"Comment":0,"Blank":0,"Complexity":0,"WeightedComplexity":0,"Hash":null,"Callback":null,"Binary":false,"Minified":false,"Generated":false},{"Language":"C Header","PossibleLanguages":["C Header"],"Filename":"output_blif.h","Extension":"h","Location":"output_blif.h","Symlocation":"","Bytes":116,"Lines":7,"Code":4,"Comment":0,"Blank":3,"Complexity":0,"WeightedComplexity":0,"Hash":null,"Callback":null,"Binary":false,"Minified":false,"Generated":false},{"Language":"C Header","PossibleLanguages":["C Header"],"Filename":"netlist_visualizer.h","Extension":"h","Location":"netlist_visualizer.h","Symlocation":"","Bytes":221,"Lines":4,"Code":3,"Comment":0,"Blank":1,"Complexity":0,"WeightedComplexity":0,"Hash":null,"Callback":null,"Binary":false,"Minified":false,"Generated":false},{"Language":"C Header","PossibleLanguages":["C Header"],"Filename":"multipliers.h","Extension":"h","Location":"multipliers.h","Symlocation":"","Bytes":2054,"Lines":54,"Code":26,"Comment":22,"Blank":6,"Complexity":0,"WeightedComplexity":0,"Hash":null,"Callback":null,"Binary":false,"Minified":false,"Generated":false},{"Language":"C Header","PossibleLanguages":["C Header"],"Filename":"verilog_preprocessor.h","Extension":"h","Location":"verilog_preprocessor.h","Symlocation":"","Bytes":2170,"Lines":88,"Code":55,"Comment":12,"Blank":21,"Complexity":0,"WeightedComplexity":0,"Hash":null,"Callback":null,"Binary":false,"Minified":false,"Generated":false},{"Language":"C Header","PossibleLanguages":["C Header"],"Filename":"output_graphcrunch_format.h","Extension":"h","Location":"output_graphcrunch_format.h","Symlocation":"","Bytes":113,"Lines":3,"Code":2,"Comment":0,"Blank":1,"Complexity":0,"WeightedComplexity":0,"Hash":null,"Callback":null,"Binary":false,"Minified":false,"Generated":false},{"Language":"C Header","PossibleLanguages":["C Header"],"Filename":"netlist_utils.h","Extension":"h","Location":"netlist_utils.h","Symlocation":"","Bytes":3240,"Lines":65,"Code":49,"Comment":5,"Blank":11,"Complexity":0,"WeightedComplexity":0,"Hash":null,"Callback":null,"Binary":false,"Minified":false,"Generated":false},{"Language":"C Header","PossibleLanguages":["C Header"],"Filename":"hard_blocks.h","Extension":"h","Location":"hard_blocks.h","Symlocation":"","Bytes":1698,"Lines":43,"Code":14,"Comment":22,"Blank":7,"Complexity":0,"WeightedComplexity":0,"Hash":null,"Callback":null,"Binary":false,"Minified":false,"Generated":false},{"Language":"C Header","PossibleLanguages":["C Header"],"Filename":"node_creation_library.h","Extension":"h","Location":"node_creation_library.h","Symlocation":"","Bytes":1253,"Lines":21,"Code":15,"Comment":0,"Blank":6,"Complexity":0,"WeightedComplexity":0,"Hash":null,"Callback":null,"Binary":false,"Minified":false,"Generated":false},{"Language":"C Header","PossibleLanguages":["C Header"],"Filename":"parse_making_ast.h","Extension":"h","Location":"parse_making_ast.h","Symlocation":"","Bytes":3545,"Lines":64,"Code":42,"Comment":10,"Blank":12,"Complexity":0,"WeightedComplexity":0,"Hash":null,"Callback":null,"Binary":false,"Minified":false,"Generated":false}]},{"Name":"C","Bytes":851678,"CodeBytes":0,"Lines":25631,"Code":17778,"Comment":4609,"Blank":3244,"Complexity":4079,"Count":32,"WeightedComplexity":0,"Files":[{"Language":"C","PossibleLanguages":["C"],"Filename":"ast_optimizations.c","Extension":"c","Location":"ast_optimizations.c","Symlocation":"","Bytes":10906,"Lines":344,"Code":239,"Comment":74,"Blank":31,"Complexity":51,"WeightedComplexity":0,"Hash":null,"Callback":null,"Binary":false,"Minified":false,"Generated":false},{"Language":"C","PossibleLanguages":["C"],"Filename":"errors.c","Extension":"c","Location":"errors.c","Symlocation":"","Bytes":3087,"Lines":89,"Code":49,"Comment":30,"Blank":10,"Complexity":16,"WeightedComplexity":0,"Hash":null,"Callback":null,"Binary":false,"Minified":false,"Generated":false},{"Language":"C","PossibleLanguages":["C"],"Filename":"queue.c","Extension":"c","Location":"queue.c","Symlocation":"","Bytes":2673,"Lines":113,"Code":75,"Comment":22,"Blank":16,"Complexity":7,"WeightedComplexity":0,"Hash":null,"Callback":null,"Binary":false,"Minified":false,"Generated":false},{"Language":"C","PossibleLanguages":["C"],"Filename":"activity_estimation.c","Extension":"c","Location":"activity_estimation.c","Symlocation":"","Bytes":32327,"Lines":876,"Code":614,"Comment":143,"Blank":119,"Complexity":186,"WeightedComplexity":0,"Hash":null,"Callback":null,"Binary":false,"Minified":false,"Generated":false},{"Language":"C","PossibleLanguages":["C"],"Filename":"hashtable.c","Extension":"c","Location":"hashtable.c","Symlocation":"","Bytes":5598,"Lines":199,"Code":148,"Comment":22,"Blank":29,"Complexity":13,"WeightedComplexity":0,"Hash":null,"Callback":null,"Binary":false,"Minified":false,"Generated":false},{"Language":"C","PossibleLanguages":["C"],"Filename":"ast_util.c","Extension":"c","Location":"ast_util.c","Symlocation":"","Bytes":32837,"Lines":908,"Code":674,"Comment":134,"Blank":100,"Complexity":211,"WeightedComplexity":0,"Hash":null,"Callback":null,"Binary":false,"Minified":false,"Generated":false},{"Language":"C","PossibleLanguages":["C"],"Filename":"netlist_check.c","Extension":"c","Location":"netlist_check.c","Symlocation":"","Bytes":33740,"Lines":833,"Code":588,"Comment":152,"Blank":93,"Complexity":200,"WeightedComplexity":0,"Hash":null,"Callback":null,"Binary":false,"Minified":false,"Generated":false},{"Language":"C","PossibleLanguages":["C"],"Filename":"read_xml_config_file.c","Extension":"c","Location":"read_xml_config_file.c","Symlocation":"","Bytes":8971,"Lines":308,"Code":221,"Comment":51,"Blank":36,"Complexity":55,"WeightedComplexity":0,"Hash":null,"Callback":null,"Binary":false,"Minified":false,"Generated":false},{"Language":"C","PossibleLanguages":["C"],"Filename":"read_netlist.c","Extension":"c","Location":"read_netlist.c","Symlocation":"","Bytes":23385,"Lines":698,"Code":476,"Comment":130,"Blank":92,"Complexity":96,"WeightedComplexity":0,"Hash":null,"Callback":null,"Binary":false,"Minified":false,"Generated":false},{"Language":"C","PossibleLanguages":["C"],"Filename":"string_cache.c","Extension":"c","Location":"string_cache.c","Symlocation":"","Bytes":3872,"Lines":183,"Code":161,"Comment":2,"Blank":20,"Complexity":27,"WeightedComplexity":0,"Hash":null,"Callback":null,"Binary":false,"Minified":false,"Generated":false},{"Language":"C","PossibleLanguages":["C"],"Filename":"odin_ii.c","Extension":"c","Location":"odin_ii.c","Symlocation":"","Bytes":15821,"Lines":468,"Code":351,"Comment":71,"Blank":46,"Complexity":30,"WeightedComplexity":0,"Hash":null,"Callback":null,"Binary":false,"Minified":false,"Generated":false},{"Language":"C","PossibleLanguages":["C"],"Filename":"implicit_memory.c","Extension":"c","Location":"implicit_memory.c","Symlocation":"","Bytes":11730,"Lines":345,"Code":212,"Comment":90,"Blank":43,"Complexity":64,"WeightedComplexity":0,"Hash":null,"Callback":null,"Binary":false,"Minified":false,"Generated":false},{"Language":"C","PossibleLanguages":["C"],"Filename":"read_blif.c","Extension":"c","Location":"read_blif.c","Symlocation":"","Bytes":52973,"Lines":1637,"Code":1094,"Comment":298,"Blank":245,"Complexity":320,"WeightedComplexity":0,"Hash":null,"Callback":null,"Binary":false,"Minified":false,"Generated":false},{"Language":"C","PossibleLanguages":["C"],"Filename":"outputs.c","Extension":"c","Location":"outputs.c","Symlocation":"","Bytes":1824,"Lines":49,"Code":19,"Comment":28,"Blank":2,"Complexity":0,"WeightedComplexity":0,"Hash":null,"Callback":null,"Binary":false,"Minified":false,"Generated":false},{"Language":"C","PossibleLanguages":["C"],"Filename":"high_level_data.c","Extension":"c","Location":"high_level_data.c","Symlocation":"","Bytes":3259,"Lines":137,"Code":104,"Comment":17,"Blank":16,"Complexity":14,"WeightedComplexity":0,"Hash":null,"Callback":null,"Binary":false,"Minified":false,"Generated":false},{"Language":"C","PossibleLanguages":["C"],"Filename":"output_graphcrunch_format.c","Extension":"c","Location":"output_graphcrunch_format.c","Symlocation":"","Bytes":4928,"Lines":141,"Code":79,"Comment":44,"Blank":18,"Complexity":21,"WeightedComplexity":0,"Hash":null,"Callback":null,"Binary":false,"Minified":false,"Generated":false},{"Language":"C","PossibleLanguages":["C"],"Filename":"hard_blocks.c","Extension":"c","Location":"hard_blocks.c","Symlocation":"","Bytes":8543,"Lines":350,"Code":263,"Comment":30,"Blank":57,"Complexity":76,"WeightedComplexity":0,"Hash":null,"Callback":null,"Binary":false,"Minified":false,"Generated":false},{"Language":"C","PossibleLanguages":["C"],"Filename":"netlist_optimizations.c","Extension":"c","Location":"netlist_optimizations.c","Symlocation":"","Bytes":1846,"Lines":51,"Code":21,"Comment":27,"Blank":3,"Complexity":0,"WeightedComplexity":0,"Hash":null,"Callback":null,"Binary":false,"Minified":false,"Generated":false},{"Language":"C","PossibleLanguages":["C"],"Filename":"multipliers.c","Extension":"c","Location":"multipliers.c","Symlocation":"","Bytes":36544,"Lines":1142,"Code":759,"Comment":250,"Blank":133,"Complexity":165,"WeightedComplexity":0,"Hash":null,"Callback":null,"Binary":false,"Minified":false,"Generated":false},{"Language":"C","PossibleLanguages":["C"],"Filename":"print_netlist.c","Extension":"c","Location":"print_netlist.c","Symlocation":"","Bytes":15222,"Lines":336,"Code":276,"Comment":31,"Blank":29,"Complexity":40,"WeightedComplexity":0,"Hash":null,"Callback":null,"Binary":false,"Minified":false,"Generated":false},{"Language":"C","PossibleLanguages":["C"],"Filename":"odin_util.c","Extension":"c","Location":"odin_util.c","Symlocation":"","Bytes":18289,"Lines":650,"Code":416,"Comment":153,"Blank":81,"Complexity":106,"WeightedComplexity":0,"Hash":null,"Callback":null,"Binary":false,"Minified":false,"Generated":false},{"Language":"C","PossibleLanguages":["C"],"Filename":"simulate_blif.c","Extension":"c","Location":"simulate_blif.c","Symlocation":"","Bytes":89235,"Lines":3210,"Code":2274,"Comment":545,"Blank":391,"Complexity":663,"WeightedComplexity":0,"Hash":null,"Callback":null,"Binary":false,"Minified":false,"Generated":false},{"Language":"C","PossibleLanguages":["C"],"Filename":"netlist_stats.c","Extension":"c","Location":"netlist_stats.c","Symlocation":"","Bytes":15258,"Lines":438,"Code":260,"Comment":115,"Blank":63,"Complexity":50,"WeightedComplexity":0,"Hash":null,"Callback":null,"Binary":false,"Minified":false,"Generated":false},{"Language":"C","PossibleLanguages":["C"],"Filename":"partial_map.c","Extension":"c","Location":"partial_map.c","Symlocation":"","Bytes":41241,"Lines":1268,"Code":922,"Comment":211,"Blank":135,"Complexity":158,"WeightedComplexity":0,"Hash":null,"Callback":null,"Binary":false,"Minified":false,"Generated":false},{"Language":"C","PossibleLanguages":["C"],"Filename":"netlist_utils.c","Extension":"c","Location":"netlist_utils.c","Symlocation":"","Bytes":35943,"Lines":1081,"Code":706,"Comment":235,"Blank":140,"Complexity":137,"WeightedComplexity":0,"Hash":null,"Callback":null,"Binary":false,"Minified":false,"Generated":false},{"Language":"C","PossibleLanguages":["C"],"Filename":"verilog_preprocessor.c","Extension":"c","Location":"verilog_preprocessor.c","Symlocation":"","Bytes":19390,"Lines":686,"Code":499,"Comment":107,"Blank":80,"Complexity":151,"WeightedComplexity":0,"Hash":null,"Callback":null,"Binary":false,"Minified":false,"Generated":false},{"Language":"C","PossibleLanguages":["C"],"Filename":"memories.c","Extension":"c","Location":"memories.c","Symlocation":"","Bytes":55283,"Lines":1733,"Code":1213,"Comment":241,"Blank":279,"Complexity":239,"WeightedComplexity":0,"Hash":null,"Callback":null,"Binary":false,"Minified":false,"Generated":false},{"Language":"C","PossibleLanguages":["C"],"Filename":"node_creation_library.c","Extension":"c","Location":"node_creation_library.c","Symlocation":"","Bytes":15458,"Lines":461,"Code":323,"Comment":90,"Blank":48,"Complexity":1,"WeightedComplexity":0,"Hash":null,"Callback":null,"Binary":false,"Minified":false,"Generated":false},{"Language":"C","PossibleLanguages":["C"],"Filename":"output_blif.c","Extension":"c","Location":"output_blif.c","Symlocation":"","Bytes":23627,"Lines":762,"Code":578,"Comment":111,"Blank":73,"Complexity":151,"WeightedComplexity":0,"Hash":null,"Callback":null,"Binary":false,"Minified":false,"Generated":false},{"Language":"C","PossibleLanguages":["C"],"Filename":"netlist_visualizer.c","Extension":"c","Location":"netlist_visualizer.c","Symlocation":"","Bytes":13065,"Lines":386,"Code":258,"Comment":75,"Blank":53,"Complexity":103,"WeightedComplexity":0,"Hash":null,"Callback":null,"Binary":false,"Minified":false,"Generated":false},{"Language":"C","PossibleLanguages":["C"],"Filename":"parse_making_ast.c","Extension":"c","Location":"parse_making_ast.c","Symlocation":"","Bytes":53395,"Lines":1388,"Code":917,"Comment":310,"Blank":161,"Complexity":108,"WeightedComplexity":0,"Hash":null,"Callback":null,"Binary":false,"Minified":false,"Generated":false},{"Language":"C","PossibleLanguages":["C"],"Filename":"netlist_create_from_ast.c","Extension":"c","Location":"netlist_create_from_ast.c","Symlocation":"","Bytes":161408,"Lines":4361,"Code":2989,"Comment":770,"Blank":602,"Complexity":620,"WeightedComplexity":0,"Hash":null,"Callback":null,"Binary":false,"Minified":false,"Generated":false}]},{"Name":"Happy","Bytes":14824,"CodeBytes":0,"Lines":336,"Code":284,"Comment":0,"Blank":52,"Complexity":0,"Count":1,"WeightedComplexity":0,"Files":[{"Language":"Happy","PossibleLanguages":["Happy"],"Filename":"verilog_bison.y","Extension":"y","Location":"verilog_bison.y","Symlocation":"","Bytes":14824,"Lines":336,"Code":284,"Comment":0,"Blank":52,"Complexity":0,"WeightedComplexity":0,"Hash":null,"Callback":null,"Binary":false,"Minified":false,"Generated":false}]},{"Name":"LEX","Bytes":5324,"CodeBytes":0,"Lines":129,"Code":88,"Comment":28,"Blank":13,"Complexity":0,"Count":1,"WeightedComplexity":0,"Files":[{"Language":"LEX","PossibleLanguages":["LEX"],"Filename":"verilog_flex.l","Extension":"l","Location":"verilog_flex.l","Symlocation":"","Bytes":5324,"Lines":129,"Code":88,"Comment":28,"Blank":13,"Complexity":0,"WeightedComplexity":0,"Hash":null,"Callback":null,"Binary":false,"Minified":false,"Generated":false}]},{"Name":"Makefile","Bytes":127,"CodeBytes":0,"Lines":6,"Code":4,"Comment":2,"Blank":0,"Complexity":0,"Count":1,"WeightedComplexity":0,"Files":[{"Language":"Makefile","PossibleLanguages":["Makefile"],"Filename":"Makefile","Extension":"Makefile","Location":"Makefile","Symlocation":"","Bytes":127,"Lines":6,"Code":4,"Comment":2,"Blank":0,"Complexity":0,"WeightedComplexity":0,"Hash":null,"Callback":null,"Binary":false,"Minified":false,"Generated":false}]}]