{"adders.cpp": {"h_volume": 66546.4989158913, "h_length": 8014, "h_voc": 316, "distinct_operators": 105, "distinct_operands": 211}, "ast_elaborate.cpp": {"h_volume": 127655.31588322048, "h_length": 14831, "h_voc": 390, "distinct_operators": 134, "distinct_operands": 256}, "ast_loop_unroll.cpp": {"h_volume": 18646.45129878271, "h_length": 2481, "h_voc": 183, "distinct_operators": 86, "distinct_operands": 97}, "ast_util.cpp": {"h_volume": 66704.6870141819, "h_length": 7973, "h_voc": 330, "distinct_operators": 148, "distinct_operands": 182}, "BLIF.cpp": {"h_volume": -1, "h_length": 0, "h_voc": 0, "distinct_operators": 0, "distinct_operands": 0}, "BLIFElaborate.cpp": {"h_volume": 9745.19099407628, "h_length": 1421, "h_voc": 116, "distinct_operators": 72, "distinct_operands": 44}, "BLIFReader.cpp": {"h_volume": 94856.40586211516, "h_length": 10739, "h_voc": 456, "distinct_operators": 159, "distinct_operands": 297}, "BLIFWriter.cpp": {"h_volume": 17211.164346979018, "h_length": 2315, "h_voc": 173, "distinct_operators": 79, "distinct_operands": 94}, "BlockMemories.cpp": {"h_volume": 63368.33507260697, "h_length": 7805, "h_voc": 278, "distinct_operators": 110, "distinct_operands": 168}, "CaseEqual.cpp": {"h_volume": 3563.823058094895, "h_length": 567, "h_voc": 78, "distinct_operators": 45, "distinct_operands": 33}, "Division.cpp": {"h_volume": 16474.477795640112, "h_length": 2279, "h_voc": 150, "distinct_operators": 65, "distinct_operands": 85}, "enum_str.cpp": {"h_volume": 9461.217937204745, "h_length": 1589, "h_voc": 62, "distinct_operators": 4, "distinct_operands": 58}, "FlipFlop.cpp": {"h_volume": 13760.962339887645, "h_length": 2147, "h_voc": 85, "distinct_operators": 31, "distinct_operands": 54}, "GenericIO.cpp": {"h_volume": 101.43760004615399, "h_length": 32, "h_voc": 9, "distinct_operators": 6, "distinct_operands": 3}, "GenericReader.cpp": {"h_volume": 895.172054701737, "h_length": 163, "h_voc": 45, "distinct_operators": 30, "distinct_operands": 15}, "GenericWriter.cpp": {"h_volume": 1361.9795678897594, "h_length": 248, "h_voc": 45, "distinct_operators": 28, "distinct_operands": 17}, "HardSoftLogicMixer.cpp": {"h_volume": 1215.1836303325429, "h_length": 220, "h_voc": 46, "distinct_operators": 32, "distinct_operands": 14}, "hard_blocks.cpp": {"h_volume": 11368.741920371622, "h_length": 1646, "h_voc": 120, "distinct_operators": 52, "distinct_operands": 68}, "Hashtable.cpp": {"h_volume": 595.0, "h_length": 119, "h_voc": 32, "distinct_operators": 23, "distinct_operands": 9}, "hierarchy_util.cpp": {"h_volume": 10634.714438664667, "h_length": 1615, "h_voc": 96, "distinct_operators": 51, "distinct_operands": 45}, "implicit_memory.cpp": {"h_volume": 12500.408761918885, "h_length": 1691, "h_voc": 168, "distinct_operators": 79, "distinct_operands": 89}, "Latch.cpp": {"h_volume": 5596.044528121466, "h_length": 846, "h_voc": 98, "distinct_operators": 39, "distinct_operands": 59}, "LogicalOps.cpp": {"h_volume": 5444.2872539921755, "h_length": 845, "h_voc": 87, "distinct_operators": 44, "distinct_operands": 43}, "memories.cpp": {"h_volume": 102937.36765223701, "h_length": 12033, "h_voc": 376, "distinct_operators": 136, "distinct_operands": 240}, "MixingOptimization.cpp": {"h_volume": 4020.7676589278403, "h_length": 629, "h_voc": 84, "distinct_operators": 44, "distinct_operands": 40}, "Modulo.cpp": {"h_volume": 64.5293250129808, "h_length": 18, "h_voc": 12, "distinct_operators": 8, "distinct_operands": 4}, "Multiplexer.cpp": {"h_volume": 12712.35208594105, "h_length": 1871, "h_voc": 111, "distinct_operators": 58, "distinct_operands": 53}, "multipliers.cpp": {"h_volume": 82386.20389328337, "h_length": 9605, "h_voc": 382, "distinct_operators": 130, "distinct_operands": 252}, "netlist_check.cpp": {"h_volume": 29641.86733426253, "h_length": 4140, "h_voc": 143, "distinct_operators": 55, "distinct_operands": 88}, "netlist_cleanup.cpp": {"h_volume": 5582.031036087235, "h_length": 820, "h_voc": 112, "distinct_operators": 46, "distinct_operands": 66}, "netlist_create_from_ast.cpp": {"h_volume": 264915.4769974614, "h_length": 28317, "h_voc": 655, "distinct_operators": 193, "distinct_operands": 462}, "netlist_statistic.cpp": {"h_volume": 16400.389014653283, "h_length": 2314, "h_voc": 136, "distinct_operators": 60, "distinct_operands": 76}, "netlist_utils.cpp": {"h_volume": 75450.365244251, "h_length": 8781, "h_voc": 386, "distinct_operators": 113, "distinct_operands": 273}, "netlist_visualizer.cpp": {"h_volume": 11746.337743521713, "h_length": 1768, "h_voc": 100, "distinct_operators": 47, "distinct_operands": 53}, "node_creation_library.cpp": {"h_volume": 17842.149668836046, "h_length": 2357, "h_voc": 190, "distinct_operators": 70, "distinct_operands": 120}, "odin_error.cpp": {"h_volume": 4123.558861338384, "h_length": 618, "h_voc": 102, "distinct_operators": 57, "distinct_operands": 45}, "odin_ii.cpp": {"h_volume": 28549.27558325224, "h_length": 3440, "h_voc": 315, "distinct_operators": 137, "distinct_operands": 178}, "odin_memory.cpp": {"h_volume": 300.8281419610299, "h_length": 64, "h_voc": 26, "distinct_operators": 21, "distinct_operands": 5}, "odin_util.cpp": {"h_volume": 34690.68951685883, "h_length": 4180, "h_voc": 315, "distinct_operators": 133, "distinct_operands": 182}, "parse_making_ast.cpp": {"h_volume": 74084.65675181722, "h_length": 8716, "h_voc": 362, "distinct_operators": 109, "distinct_operands": 253}, "partial_map.cpp": {"h_volume": 48065.645688769306, "h_length": 5971, "h_voc": 265, "distinct_operators": 115, "distinct_operands": 150}, "Power.cpp": {"h_volume": 11507.268775637496, "h_length": 1681, "h_voc": 115, "distinct_operators": 64, "distinct_operands": 51}, "read_xml_config_file.cpp": {"h_volume": 8571.638677895171, "h_length": 1264, "h_voc": 110, "distinct_operators": 55, "distinct_operands": 55}, "scope_util.cpp": {"h_volume": 1488.6298122496069, "h_length": 268, "h_voc": 47, "distinct_operators": 30, "distinct_operands": 17}, "Shift.cpp": {"h_volume": 1842.9498658298578, "h_length": 312, "h_voc": 60, "distinct_operators": 35, "distinct_operands": 25}, "simulate_blif.cpp": {"h_volume": 149324.99831675764, "h_length": 16114, "h_voc": 616, "distinct_operators": 238, "distinct_operands": 378}, "string_cache.cpp": {"h_volume": 7206.998028171593, "h_length": 1140, "h_voc": 80, "distinct_operators": 46, "distinct_operands": 34}, "subtractions.cpp": {"h_volume": 39914.709147818925, "h_length": 5165, "h_voc": 212, "distinct_operators": 77, "distinct_operands": 135}, "Verilog.cpp": {"h_volume": -1, "h_length": 0, "h_voc": 0, "distinct_operators": 0, "distinct_operands": 0}, "VerilogReader.cpp": {"h_volume": 256.7639251168273, "h_length": 54, "h_voc": 27, "distinct_operators": 20, "distinct_operands": 7}, "VerilogWriter.cpp": {"h_volume": 3803.2824449237523, "h_length": 570, "h_voc": 102, "distinct_operators": 45, "distinct_operands": 57}, "YYosys.cpp": {"h_volume": 6751.069407421912, "h_length": 966, "h_voc": 127, "distinct_operators": 66, "distinct_operands": 61}}